_libchirp_cffi.cp36-win_amd64.pyd
libchirp/__init__.py
libchirp/asyncio.py
libchirp/pool.py
libchirp/queue.py
libchirp/version.py
libchirp-1.2.1b3.dist-info/LICENSE
libchirp-1.2.1b3.dist-info/METADATA
libchirp-1.2.1b3.dist-info/WHEEL
libchirp-1.2.1b3.dist-info/top_level.txt
libchirp-1.2.1b3.dist-info/RECORD
