Metadata-Version: 2.1
Name: libchirp
Version: 1.2.1b3
Summary: Message-passing for everyone
Home-page: https://github.com/concretecloud/python-chirp
Author: Jean-Louis Fuchs
Author-email: ganwell@fangorn.ch
License: UNKNOWN
Platform: UNKNOWN
Classifier: Development Status :: 4 - Beta
Classifier: Programming Language :: Python :: 3
Classifier: Programming Language :: Python :: Implementation :: PyPy
Classifier: License :: OSI Approved :: Mozilla Public License 2.0 (MPL 2.0)
Classifier: Topic :: System :: Networking
Requires-Dist: cffi (>=1.0.0)
